{
    "openapi": "3.0.0",
    "info": {
        "title": "API de Tarefas",
        "description": "API para gerenciamento de tarefas.",
        "contact": {
            "email": "sophiavsant@gmail.com"
        },
        "license": {
            "name": "MIT",
            "url": "https://opensource.org/licenses/MIT"
        },
        "version": "1.0.0"
    },
    "paths": {
        "/api/auth/register": {
            "post": {
                "tags": [
                    "Auth"
                ],
                "summary": "Register a new user",
                "operationId": "d764dd091cc4494ae0baf360b03319f3",
                "requestBody": {
                    "required": true,
                    "content": {
                        "application/json": {
                            "schema": {
                                "required": [
                                    "name",
                                    "email",
                                    "password",
                                    "password_confirmation"
                                ],
                                "properties": {
                                    "name": {
                                        "type": "string",
                                        "example": "John Doe"
                                    },
                                    "email": {
                                        "type": "string",
                                        "format": "email",
                                        "example": "john@example.com"
                                    },
                                    "password": {
                                        "type": "string",
                                        "format": "password",
                                        "example": "secret123"
                                    },
                                    "password_confirmation": {
                                        "type": "string",
                                        "example": "secret123"
                                    }
                                },
                                "type": "object"
                            }
                        }
                    }
                },
                "responses": {
                    "201": {
                        "description": "User registered successfully"
                    },
                    "400": {
                        "description": "Validation error"
                    }
                }
            }
        },
        "/api/auth/login": {
            "post": {
                "tags": [
                    "Auth"
                ],
                "summary": "User login",
                "operationId": "8dcb70df1020986038d098cc08d05dae",
                "requestBody": {
                    "required": true,
                    "content": {
                        "application/json": {
                            "schema": {
                                "required": [
                                    "email",
                                    "password"
                                ],
                                "properties": {
                                    "email": {
                                        "type": "string",
                                        "format": "email",
                                        "example": "john@example.com"
                                    },
                                    "password": {
                                        "type": "string",
                                        "format": "password",
                                        "example": "secret123"
                                    }
                                },
                                "type": "object"
                            }
                        }
                    }
                },
                "responses": {
                    "200": {
                        "description": "Login successful"
                    },
                    "401": {
                        "description": "Invalid credentials"
                    }
                }
            }
        },
        "/api/auth/logout": {
            "post": {
                "tags": [
                    "Auth"
                ],
                "summary": "User logout",
                "operationId": "69281b12abb272c76871f19cb17ca563",
                "requestBody": {
                    "required": true,
                    "content": {
                        "application/json": {
                            "schema": {
                                "required": [
                                    "user"
                                ],
                                "properties": {
                                    "user": {
                                        "type": "object",
                                        "example": {
                                            "id": 1
                                        }
                                    }
                                },
                                "type": "object"
                            }
                        }
                    }
                },
                "responses": {
                    "200": {
                        "description": "Logout realizado com sucesso",
                        "content": {
                            "application/json": {
                                "schema": {
                                    "properties": {
                                        "message": {
                                            "type": "string",
                                            "example": "Logout realizado com sucesso"
                                        }
                                    },
                                    "type": "object"
                                }
                            }
                        }
                    },
                    "401": {
                        "description": "Usuário não autenticado"
                    }
                }
            }
        },
        "/api/categories": {
            "get": {
                "tags": [
                    "Categories"
                ],
                "summary": "Get all categories",
                "operationId": "3f5817a34833d0a1f4af4548dd3aeaba",
                "responses": {
                    "200": {
                        "description": "List of categories"
                    }
                },
                "security": [
                    {
                        "sanctum": []
                    }
                ]
            },
            "post": {
                "tags": [
                    "Categories"
                ],
                "summary": "Create a new category",
                "operationId": "71fcad552bb0eaba9fb191fd8d8dcab0",
                "requestBody": {
                    "required": true,
                    "content": {
                        "application/json": {
                            "schema": {
                                "required": [
                                    "name"
                                ],
                                "properties": {
                                    "name": {
                                        "type": "string",
                                        "example": "Work"
                                    }
                                },
                                "type": "object"
                            }
                        }
                    }
                },
                "responses": {
                    "201": {
                        "description": "Category created successfully"
                    },
                    "400": {
                        "description": "Validation error"
                    }
                },
                "security": [
                    {
                        "sanctum": []
                    }
                ]
            }
        },
        "/api/categories/{id}": {
            "get": {
                "tags": [
                    "Categories"
                ],
                "summary": "Get category",
                "operationId": "c68e76d323c008827a9e47398b1583de",
                "parameters": [
                    {
                        "name": "id",
                        "in": "path",
                        "required": true,
                        "schema": {
                            "type": "integer"
                        }
                    }
                ],
                "responses": {
                    "200": {
                        "description": "List of categories"
                    }
                },
                "security": [
                    {
                        "sanctum": []
                    }
                ]
            },
            "put": {
                "tags": [
                    "Categories"
                ],
                "summary": "Update a category",
                "operationId": "0e686b2748211cc688333ed705dc111f",
                "parameters": [
                    {
                        "name": "id",
                        "in": "path",
                        "required": true,
                        "schema": {
                            "type": "integer"
                        }
                    }
                ],
                "requestBody": {
                    "required": true,
                    "content": {
                        "application/json": {
                            "schema": {
                                "required": [
                                    "name"
                                ],
                                "properties": {
                                    "name": {
                                        "type": "string",
                                        "example": "Updated Name"
                                    }
                                },
                                "type": "object"
                            }
                        }
                    }
                },
                "responses": {
                    "200": {
                        "description": "Category updated successfully"
                    },
                    "404": {
                        "description": "Category not found"
                    }
                },
                "security": [
                    {
                        "sanctum": []
                    }
                ]
            },
            "delete": {
                "tags": [
                    "Categories"
                ],
                "summary": "Delete a category",
                "operationId": "4c12e22a7f8c617bd83bfa1fdc05428d",
                "parameters": [
                    {
                        "name": "id",
                        "in": "path",
                        "required": true,
                        "schema": {
                            "type": "integer"
                        }
                    }
                ],
                "responses": {
                    "200": {
                        "description": "Category deleted successfully"
                    },
                    "404": {
                        "description": "Category not found"
                    }
                },
                "security": [
                    {
                        "sanctum": []
                    }
                ]
            }
        },
        "/api/tasks": {
            "get": {
                "tags": [
                    "Tasks"
                ],
                "summary": "Get all tasks of the authenticated user",
                "operationId": "471d938a3bfaeb6fbd981d7c3e2728b0",
                "parameters": [
                    {
                        "name": "status",
                        "in": "query",
                        "description": "Filter tasks by status (pendente, em andamento, concluído)",
                        "required": false,
                        "schema": {
                            "type": "string",
                            "enum": [
                                "pendente",
                                "em andamento",
                                "concluído"
                            ]
                        }
                    },
                    {
                        "name": "category_id",
                        "in": "query",
                        "description": "Filter tasks by category ID",
                        "required": false,
                        "schema": {
                            "type": "integer",
                            "example": 1
                        }
                    },
                    {
                        "name": "sort_by",
                        "in": "query",
                        "description": "Sort by field (default: created_at)",
                        "required": false,
                        "schema": {
                            "type": "string",
                            "example": "title"
                        }
                    },
                    {
                        "name": "sort_order",
                        "in": "query",
                        "description": "Sort order (asc or desc, default: desc)",
                        "required": false,
                        "schema": {
                            "type": "string",
                            "enum": [
                                "asc",
                                "desc"
                            ]
                        }
                    },
                    {
                        "name": "per_page",
                        "in": "query",
                        "description": "Number of tasks per page (default: 10)",
                        "required": false,
                        "schema": {
                            "type": "integer",
                            "example": 10
                        }
                    }
                ],
                "responses": {
                    "200": {
                        "description": "List of user tasks",
                        "content": {
                            "application/json": {
                                "schema": {
                                    "properties": {
                                        "current_page": {
                                            "type": "integer",
                                            "example": 1
                                        },
                                        "data": {
                                            "type": "array",
                                            "items": {
                                                "properties": {
                                                    "id": {
                                                        "type": "integer",
                                                        "example": 1
                                                    },
                                                    "title": {
                                                        "type": "string",
                                                        "example": "Complete project documentation"
                                                    },
                                                    "category_id": {
                                                        "type": "integer",
                                                        "example": 1
                                                    },
                                                    "status": {
                                                        "type": "string",
                                                        "example": "pendente"
                                                    },
                                                    "created_at": {
                                                        "type": "string",
                                                        "format": "date-time",
                                                        "example": "2025-02-06T12:00:00Z"
                                                    }
                                                },
                                                "type": "object"
                                            }
                                        },
                                        "total": {
                                            "type": "integer",
                                            "example": 50
                                        },
                                        "per_page": {
                                            "type": "integer",
                                            "example": 10
                                        },
                                        "last_page": {
                                            "type": "integer",
                                            "example": 5
                                        }
                                    },
                                    "type": "object"
                                }
                            }
                        }
                    },
                    "401": {
                        "description": "Unauthorized access",
                        "content": {
                            "application/json": {
                                "schema": {
                                    "properties": {
                                        "message": {
                                            "type": "string",
                                            "example": "Unauthorized"
                                        }
                                    },
                                    "type": "object"
                                }
                            }
                        }
                    }
                },
                "security": [
                    {
                        "sanctum": []
                    }
                ]
            },
            "post": {
                "tags": [
                    "Tasks"
                ],
                "summary": "Create a new task",
                "operationId": "f803ebdb2300acdb7e93bbe8d0b9a2e8",
                "requestBody": {
                    "required": true,
                    "content": {
                        "application/json": {
                            "schema": {
                                "required": [
                                    "title",
                                    "category_id"
                                ],
                                "properties": {
                                    "title": {
                                        "type": "string",
                                        "example": "Complete project documentation"
                                    },
                                    "category_id": {
                                        "type": "integer",
                                        "example": 1
                                    },
                                    "status": {
                                        "type": "string",
                                        "enum": [
                                            "pendente",
                                            "em andamento",
                                            "concluído"
                                        ],
                                        "example": "pendente"
                                    }
                                },
                                "type": "object"
                            }
                        }
                    }
                },
                "responses": {
                    "201": {
                        "description": "Task created successfully",
                        "content": {
                            "application/json": {
                                "schema": {
                                    "properties": {
                                        "id": {
                                            "type": "integer",
                                            "example": 101
                                        },
                                        "title": {
                                            "type": "string",
                                            "example": "Complete project documentation"
                                        },
                                        "category_id": {
                                            "type": "integer",
                                            "example": 1
                                        },
                                        "status": {
                                            "type": "string",
                                            "enum": [
                                                "pendente",
                                                "em andamento",
                                                "concluído"
                                            ],
                                            "example": "pendente"
                                        }
                                    },
                                    "type": "object"
                                }
                            }
                        }
                    },
                    "400": {
                        "description": "Validation error",
                        "content": {
                            "application/json": {
                                "schema": {
                                    "properties": {
                                        "message": {
                                            "type": "string",
                                            "example": "The title field is required."
                                        }
                                    },
                                    "type": "object"
                                }
                            }
                        }
                    }
                },
                "security": [
                    {
                        "sanctum": []
                    }
                ]
            }
        },
        "/api/tasks/{id}": {
            "get": {
                "tags": [
                    "Tasks"
                ],
                "summary": "Get a task of the authenticated user",
                "operationId": "90b3cd4d2d4b416dc989d2055dbed06c",
                "parameters": [
                    {
                        "name": "id",
                        "in": "path",
                        "required": true,
                        "schema": {
                            "type": "integer"
                        }
                    }
                ],
                "responses": {
                    "200": {
                        "description": "User task",
                        "content": {
                            "application/json": {
                                "schema": {
                                    "type": "array",
                                    "items": {
                                        "properties": {
                                            "id": {
                                                "type": "integer",
                                                "example": 1
                                            },
                                            "title": {
                                                "type": "string",
                                                "example": "Complete project documentation"
                                            },
                                            "category_id": {
                                                "type": "integer",
                                                "example": 1
                                            }
                                        },
                                        "type": "object"
                                    }
                                }
                            }
                        }
                    },
                    "401": {
                        "description": "Unauthorized access",
                        "content": {
                            "application/json": {
                                "schema": {
                                    "properties": {
                                        "message": {
                                            "type": "string",
                                            "example": "Unauthorized"
                                        }
                                    },
                                    "type": "object"
                                }
                            }
                        }
                    }
                },
                "security": [
                    {
                        "sanctum": []
                    }
                ]
            },
            "put": {
                "tags": [
                    "Tasks"
                ],
                "summary": "Update a task",
                "operationId": "1aaf37e74360ef4c10fadaee02ae77fb",
                "parameters": [
                    {
                        "name": "id",
                        "in": "path",
                        "description": "ID of the task to update",
                        "required": true,
                        "schema": {
                            "type": "integer",
                            "example": 1
                        }
                    }
                ],
                "requestBody": {
                    "required": true,
                    "content": {
                        "application/json": {
                            "schema": {
                                "required": [
                                    "title",
                                    "category_id"
                                ],
                                "properties": {
                                    "title": {
                                        "type": "string",
                                        "example": "Complete updated project documentation"
                                    },
                                    "category_id": {
                                        "type": "integer",
                                        "example": 1
                                    },
                                    "status": {
                                        "type": "string",
                                        "enum": [
                                            "pendente",
                                            "em andamento",
                                            "concluído"
                                        ],
                                        "example": "pendente"
                                    }
                                },
                                "type": "object"
                            }
                        }
                    }
                },
                "responses": {
                    "200": {
                        "description": "Task updated successfully",
                        "content": {
                            "application/json": {
                                "schema": {
                                    "properties": {
                                        "id": {
                                            "type": "integer",
                                            "example": 1
                                        },
                                        "title": {
                                            "type": "string",
                                            "example": "Complete updated project documentation"
                                        },
                                        "category_id": {
                                            "type": "integer",
                                            "example": 1
                                        },
                                        "status": {
                                            "type": "string",
                                            "enum": [
                                                "pendente",
                                                "em andamento",
                                                "concluído"
                                            ],
                                            "example": "pendente"
                                        }
                                    },
                                    "type": "object"
                                }
                            }
                        }
                    },
                    "400": {
                        "description": "Validation error",
                        "content": {
                            "application/json": {
                                "schema": {
                                    "properties": {
                                        "message": {
                                            "type": "string",
                                            "example": "The title field is required."
                                        }
                                    },
                                    "type": "object"
                                }
                            }
                        }
                    }
                },
                "security": [
                    {
                        "sanctum": []
                    }
                ]
            },
            "delete": {
                "tags": [
                    "Tasks"
                ],
                "summary": "Delete a task",
                "operationId": "ad582480cd57c2a4e3b6a426943eeca5",
                "parameters": [
                    {
                        "name": "id",
                        "in": "path",
                        "description": "ID of the task to delete",
                        "required": true,
                        "schema": {
                            "type": "integer",
                            "example": 1
                        }
                    }
                ],
                "responses": {
                    "200": {
                        "description": "Task deleted successfully",
                        "content": {
                            "application/json": {
                                "schema": {
                                    "properties": {
                                        "message": {
                                            "type": "string",
                                            "example": "Task deleted successfully"
                                        }
                                    },
                                    "type": "object"
                                }
                            }
                        }
                    },
                    "404": {
                        "description": "Task not found",
                        "content": {
                            "application/json": {
                                "schema": {
                                    "properties": {
                                        "message": {
                                            "type": "string",
                                            "example": "Task not found"
                                        }
                                    },
                                    "type": "object"
                                }
                            }
                        }
                    }
                },
                "security": [
                    {
                        "sanctum": []
                    }
                ]
            }
        }
    },
    "tags": [
        {
            "name": "Auth",
            "description": "Auth"
        },
        {
            "name": "Categories",
            "description": "Categories"
        },
        {
            "name": "Tasks",
            "description": "Tasks"
        }
    ],
    "components": {
        "securitySchemes": {
            "sanctum": {
                "type": "apiKey",
                "description": "Enter token in format (Bearer <token>)",
                "name": "Authorization",
                "in": "header"
            }
        }
    },
    "security": {
        "sanctum": {
            "type": "apiKey",
            "description": "Bearer",
            "name": "Authorization",
            "in": "header"
        }
    }
}